odoo8_addon_stock_picking_invoicing_unified-8.0.1.0.0.99.dev20-py2.7-nspkg.pth
odoo8_addon_stock_picking_invoicing_unified-8.0.1.0.0.99.dev20.dist-info/METADATA
odoo8_addon_stock_picking_invoicing_unified-8.0.1.0.0.99.dev20.dist-info/RECORD
odoo8_addon_stock_picking_invoicing_unified-8.0.1.0.0.99.dev20.dist-info/WHEEL
odoo8_addon_stock_picking_invoicing_unified-8.0.1.0.0.99.dev20.dist-info/namespace_packages.txt
odoo8_addon_stock_picking_invoicing_unified-8.0.1.0.0.99.dev20.dist-info/top_level.txt
odoo_addons/stock_picking_invoicing_unified/README.rst
odoo_addons/stock_picking_invoicing_unified/__init__.py
odoo_addons/stock_picking_invoicing_unified/__openerp__.py
odoo_addons/stock_picking_invoicing_unified/i18n/ca.po
odoo_addons/stock_picking_invoicing_unified/i18n/de.po
odoo_addons/stock_picking_invoicing_unified/i18n/es.po
odoo_addons/stock_picking_invoicing_unified/i18n/es_AR.po
odoo_addons/stock_picking_invoicing_unified/i18n/es_MX.po
odoo_addons/stock_picking_invoicing_unified/i18n/fi.po
odoo_addons/stock_picking_invoicing_unified/i18n/fr.po
odoo_addons/stock_picking_invoicing_unified/i18n/hr.po
odoo_addons/stock_picking_invoicing_unified/i18n/it.po
odoo_addons/stock_picking_invoicing_unified/i18n/pt.po
odoo_addons/stock_picking_invoicing_unified/i18n/pt_BR.po
odoo_addons/stock_picking_invoicing_unified/i18n/sl.po
odoo_addons/stock_picking_invoicing_unified/i18n/tr.po
odoo_addons/stock_picking_invoicing_unified/i18n/tr_TR.po
odoo_addons/stock_picking_invoicing_unified/models/__init__.py
odoo_addons/stock_picking_invoicing_unified/models/stock_move.py
odoo_addons/stock_picking_invoicing_unified/static/description/icon.png
odoo_addons/stock_picking_invoicing_unified/wizard/__init__.py
odoo_addons/stock_picking_invoicing_unified/wizard/stock_invoice_onshipping.py
odoo_addons/stock_picking_invoicing_unified/wizard/stock_invoice_onshipping_view.xml
