Metadata-Version: 2.1
Name: odoo8-addon-stock-picking-invoicing-unified
Version: 8.0.1.0.0.99.dev20
Summary: Create invoices/refunds from pickings of different types
Home-page: http://github.com/OCA/account-invoicing
Author: Serv. Tecnol. Avanzados - Pedro M. Baeza, AvanzOSC, Odoo Community Association (OCA)
Author-email: support@odoo-community.org
License: AGPL-3
Platform: UNKNOWN
Classifier: Programming Language :: Python
Classifier: Framework :: Odoo
Classifier: License :: OSI Approved :: GNU Affero General Public License v3
Requires-Python: ~=2.7
Requires-Dist: odoo (<9.0a,>=8.0a)
